blockdivision/find_embeddings.py
blockdivision/gpt_shortening.py
blockdivision/parse_subs.py
blockdivision/sentence_similarity.py
blockdivision/timecoder.py
blockdivision-0.1.0.dist-info/METADATA
blockdivision-0.1.0.dist-info/WHEEL
blockdivision-0.1.0.dist-info/RECORD
