Metadata-Version: 2.1
Name: blockdivision
Version: 0.1.0
Summary: 
Author: Batyrkhan
Author-email: batirkhangainitdinov@gmail.com
Requires-Python: >=3.8,<4.0
Classifier: Programming Language :: Python :: 3
Classifier: Programming Language :: Python :: 3.8
Classifier: Programming Language :: Python :: 3.9
Classifier: Programming Language :: Python :: 3.10
Classifier: Programming Language :: Python :: 3.11
Requires-Dist: pandas (>=2.0.1,<3.0.0)
Requires-Dist: sentence-transformers (>=2.2.2,<3.0.0)
Requires-Dist: sklearn (>=0.0.post5,<0.1)
Requires-Dist: torch (>=2.0.1,<3.0.0)
Requires-Dist: transformers[torch] (>=4.29.2,<5.0.0)
